cs/dockerutils.py
cs.dockerutils-20240519.dist-info/METADATA
cs.dockerutils-20240519.dist-info/WHEEL
cs.dockerutils-20240519.dist-info/top_level.txt
cs.dockerutils-20240519.dist-info/RECORD
