Metadata-Version: 2.1
Name: cs.dockerutils
Version: 20240519
Summary: Docker related utilities.
Author-email: Cameron Simpson <cs@cskk.id.au>
License: GNU General Public License v3 or later (GPLv3+)
Project-URL: URL, https://bitbucket.org/cameron_simpson/css/commits/all
Keywords: python3
Platform: UNKNOWN
Classifier: Programming Language :: Python
Classifier: Programming Language :: Python :: 3
Classifier: Development Status :: 4 - Beta
Classifier: Intended Audience :: Developers
Classifier: Operating System :: OS Independent
Classifier: Topic :: Software Development :: Libraries :: Python Modules
Classifier: License :: OSI Approved :: GNU General Public License v3 or later (GPLv3+)
Requires-Dist: cs.cmdutils >=20240519
Requires-Dist: cs.context >=20240412
Requires-Dist: cs.pfx >=20240412
Requires-Dist: cs.psutils >=20240316
Requires-Dist: typeguard
